jsontable2md/__init__.py
jsontable2md/converter.py
jsontable2md/json_converter.py
jsontable2md/jsontable2md.py
jsontable2md-0.1.0.dist-info/LICENSE
jsontable2md-0.1.0.dist-info/METADATA
jsontable2md-0.1.0.dist-info/WHEEL
jsontable2md-0.1.0.dist-info/top_level.txt
jsontable2md-0.1.0.dist-info/RECORD
