Metadata-Version: 2.1
Name: jsontable2md
Version: 0.1.0
Summary: Convert HTML tables embedded in JSON to Markdown extended table syntax
Home-page: https://github.com/abachan/jsontable2md
Author: abachan
Author-email: aiba1114@cl.cilas.net
License: MIT
Project-URL: Repository, https://github.com/abachan/jsontable2md
Project-URL: Issues, https://github.com/abachan/jsontable2md/issues
Keywords: markdown,html,table,conversion,json
Classifier: Development Status :: 4 - Beta
Classifier: Intended Audience :: Developers
Classifier: License :: OSI Approved :: MIT License
Classifier: Operating System :: OS Independent
Classifier: Programming Language :: Python :: 3
Classifier: Programming Language :: Python :: 3.9
Classifier: Programming Language :: Python :: 3.10
Classifier: Programming Language :: Python :: 3.11
Classifier: Programming Language :: Python :: 3.12
Classifier: Topic :: Text Processing :: Markup :: HTML
Classifier: Topic :: Text Processing :: Markup :: Markdown
Classifier: Topic :: Utilities
Requires-Python: >=3.9
License-File: LICENSE
Requires-Dist: beautifulsoup4>=4.9.0
Provides-Extra: dev
Requires-Dist: black>=23.0; extra == "dev"
Requires-Dist: isort>=5.12; extra == "dev"
Requires-Dist: mypy>=1.0; extra == "dev"
Requires-Dist: pytest>=7.0; extra == "dev"
Requires-Dist: build; extra == "dev"
Requires-Dist: twine; extra == "dev"
Requires-Dist: types-beautifulsoup4; python_version >= "3.9" and extra == "dev"
